gcpsight/__init__.py
gcpsight/gcp_scanner.py
gcpsight/gemini_processor.py
gcpsight/main.py
gcpsight/security_scorer.py
gcpsight-0.1.0.dist-info/licenses/LICENSE
gcpsight-0.1.0.dist-info/METADATA
gcpsight-0.1.0.dist-info/WHEEL
gcpsight-0.1.0.dist-info/entry_points.txt
gcpsight-0.1.0.dist-info/top_level.txt
gcpsight-0.1.0.dist-info/RECORD
