Metadata-Version: 2.4
Name: gcpsight
Version: 0.1.0
Summary: A CLI tool for GCP Security Analysis powered by Gemini.
Author-email: Rishab Kumar <rishabkumar7@gmail.com>
Project-URL: Homepage, https://github.com/rishabkumar7/gcpsight
Project-URL: Bug Tracker, https://github.com/rishabkumar7/gcpsight/issues
Keywords: gcp,security,cli,gemini,google-cloud
Classifier: Programming Language :: Python :: 3
Classifier: Operating System :: OS Independent
Classifier: Development Status :: 3 - Alpha
Classifier: Intended Audience :: Developers
Classifier: Topic :: Security
Requires-Python: >=3.10
License-File: LICENSE
Requires-Dist: google-cloud-compute~=1.14
Requires-Dist: google-cloud-storage~=2.16
Requires-Dist: google-cloud-resource-manager~=1.12
Requires-Dist: google-cloud-bigquery~=3.20
Requires-Dist: google-cloud-functions~=1.8
Requires-Dist: google-generativeai~=0.7
Requires-Dist: python-dotenv~=1.0
Requires-Dist: click~=8.1
Requires-Dist: tabulate~=0.9.0
Requires-Dist: rich~=13.7
Dynamic: license-file
